[
    {
        "local":"101 Brasa Burger",
        "localizacao":"Vila Velha - ES",
        "nome":"GTO",
        "descricao":"2 Carnes, queijo mussarela e cheddar, costela desfiada, bacon e molho 101!",
        "foto":"assets/img/101.PNG",
        "preco":35
     },
     {
        "local":"Korujão Lanches",
        "localizacao":"Vila Velha - ES",
        "nome":"Triplo Cheddar Bacon",
        "descricao":"2 Carnes, queijo mussarela e cheddar, costela desfiada, bacon e molho 101!",
        "foto":"assets/img/korujao.PNG",
        "preco":19
     },
     {
        "local":"Gol Burger",
        "localizacao":"Vila Velha - ES",
        "nome":"PIRLO",
        "descricao":"Hambúrguer de 150g, cheddar inglês, refogado de bacon, cogumelo e cebola, cebola crispy e fonduta de emmenthal",
        "foto":"assets/img/PIRLO.PNG",
        "preco":30
     },
     {
        "local":"Prefiro Alcides",
        "localizacao":"Vila Velha - ES",
        "nome":"GLUTEN EXPLOSION",
        "descricao":"ESCROTO (burger na brasa, bacon, maionese de chimichurri e bacon) + EMPANADA ",
        "foto":"assets/img/ALCIDES.PNG",
        "preco":36
     },
     {
        "local":"La Dolina",
        "localizacao":"Vitória - ES",
        "nome":"La Negra Bernasi",
        "descricao":"Burger em pão australiano, blend caseiro 180g, queijo prato, bacon, lâminas de alho frito, ketchup, maionese e alface.",
        "foto":"assets/img/LANEGRABERNASI.PNG",
        "preco":25
     },
     {
        "local":"Jussara´s Forno",
        "localizacao":"Vila Velha - ES",
        "nome":"Burger de TutanO",
        "descricao":"Hambúrguer 180 gr na Parrilha, Queijo Mozzarella Artelatte, Cogumelos Paris empanados e fritos, Tutano assado e molho agridoce",
        "foto":"assets/img/TUTANO.PNG",
        "preco":35
     }
]   
